tagger/__init__.py
tagger/core/error.py
tagger/core/klass.py
tagger/core/node.py
tagger/library/distag.py
tagger/library/rand.py
tagger/parser/parser.py
tagger/parser/tagger.lark
tagger/visitor/executor.py
tagger/visitor/interpreter.py
tagger/visitor/obj_builtin.py
tagger/visitor/tag_builtin.py
taggerscript-0.0.10.dist-info/LICENSE.md
taggerscript-0.0.10.dist-info/METADATA
taggerscript-0.0.10.dist-info/WHEEL
taggerscript-0.0.10.dist-info/RECORD
