Metadata-Version: 2.1
Name: taggerscript
Version: 0.0.10
Summary: Scripting language written in Python for Discord bot
License: GNU
Author: najis
Requires-Python: >=3.11,<4.0
Classifier: License :: Other/Proprietary License
Classifier: Programming Language :: Python :: 3
Classifier: Programming Language :: Python :: 3.11
Requires-Dist: lark (>=1.1.5,<2.0.0)
Requires-Dist: py-cord (>=2.3.2,<3.0.0)
